department/__init__.py
department/memberlist.py
department/offices.py
Skyline_Amedazi-0.11.dist-info/METADATA
Skyline_Amedazi-0.11.dist-info/WHEEL
Skyline_Amedazi-0.11.dist-info/top_level.txt
Skyline_Amedazi-0.11.dist-info/RECORD
