Metadata-Version: 2.1
Name: Skyline-Amedazi
Version: 0.11
Summary: Sole authorized Lord: 李甘雨
Author: Amedazi
License: UNKNOWN
Platform: UNKNOWN
